pynohup/__init__.py
pynohup/nhy_nohup.py
pynohup-1.0.2.dist-info/METADATA
pynohup-1.0.2.dist-info/WHEEL
pynohup-1.0.2.dist-info/top_level.txt
pynohup-1.0.2.dist-info/zip-safe
pynohup-1.0.2.dist-info/RECORD
