Metadata-Version: 2.1
Name: pynohup
Version: 1.0.2
Summary: this is a simple  logging package 
Home-page: http://www.nnzhp.cn/archives/646
Author: HanyangNiu
Author-email: niuhanyang@163.com
License: MIT
Keywords: pynohup python package
